adhoc/__init__.py
adhoc/adhoc.py
adhoc/config.py
adhoc/commands/__init__.py
adhoc/commands/commit.py
adhoc/commands/config.py
adhoc/commands/generate.py
adhoc/commands/init.py
adhoc/commands/watch.py
adhoc/db/__init__.py
adhoc/db/database.py
adhoc/templates/__init__.py
adhoc/templates/document_template.md
adhoc/templates/document_template.tex
adhoc/utils/__init__.py
adhoc/utils/config_utils.py
adhoc/utils/diff_utils.py
adhoc/utils/latex_utils.py
adhoc/utils/llm_utils.py
adhoc/utils/markdown_utils.py
adhoc/utils/word_utils.py
adhoc_python-1.0.2.dist-info/LICENSE
adhoc_python-1.0.2.dist-info/METADATA
adhoc_python-1.0.2.dist-info/WHEEL
adhoc_python-1.0.2.dist-info/entry_points.txt
adhoc_python-1.0.2.dist-info/top_level.txt
adhoc_python-1.0.2.dist-info/RECORD
