Metadata-Version: 2.1
Name: adhoc-python
Version: 1.0.2
Summary: Auto Document Codebase Changes in LaTeX, Markdown, or Word
Home-page: https://github.com/Zhreyu/adhoc
Author: Shreyas S
Author-email: Zhreyas1@example.com
Classifier: Programming Language :: Python :: 3
Classifier: License :: OSI Approved :: MIT License
Classifier: Operating System :: OS Independent
Requires-Python: >=3.6
License-File: LICENSE
Requires-Dist: jinja2>=3.1.4
Requires-Dist: requests>=2.32.3
Requires-Dist: watchdog>=5.0.3
Requires-Dist: python-docx>=1.1.2
Requires-Dist: ollama
